fastyaml-0.1.0.dist-info/METADATA
fastyaml-0.1.0.dist-info/WHEEL
fastyaml-0.1.0.dist-info/licenses/LICENSE-APACHE
fastyaml-0.1.0.dist-info/licenses/LICENSE-MIT
fastyaml/__init__.py
fastyaml/fastyaml.pyd
fastyaml-0.1.0.dist-info/RECORD
