Metadata-Version: 2.3
Name: fastyaml
Version: 0.1.0
Classifier: Programming Language :: Rust
Classifier: Programming Language :: Python :: Implementation :: CPython
Classifier: Programming Language :: Python :: Implementation :: PyPy
License-File: LICENSE-APACHE
License-File: LICENSE-MIT
Summary: A fast YAML parser
Keywords: yaml,parser
Author-email: MINGtoMING <3575188313@qq.com>
License: MIT or Apache-2.0
Requires-Python: >=3.10
